<?xml version="1.0" encoding="UTF-8"?>
<gallery><title><![CDATA[Plantacja mateczna Miskanta olbrzymiego - Grupa KSG Agro, Ukraine]]></title><name><![CDATA[ksg-miskant]]></name><type><![CDATA[fancybox]]></type><thumbwidth><![CDATA[180]]></thumbwidth><thumbheight><![CDATA[132]]></thumbheight><thumbcrop><![CDATA[1]]></thumbcrop><pagesize><![CDATA[]]></pagesize><width><![CDATA[]]></width><height><![CDATA[]]></height><item><filename><![CDATA[ksgagro-gallery/1.jpg]]></filename><title><![CDATA[]]></title><tags><![CDATA[]]></tags><description><![CDATA[]]></description><longitude><![CDATA[]]></longitude><latitude><![CDATA[]]></latitude><size><![CDATA[296832]]></size><width><![CDATA[922]]></width><height><![CDATA[692]]></height><width>922</width><height>692</height><size>296832</size></item><item><filename><![CDATA[ksgagro-gallery/2.jpg]]></filename><title><![CDATA[]]></title><tags><![CDATA[]]></tags><description><![CDATA[]]></description><longitude><![CDATA[]]></longitude><latitude><![CDATA[]]></latitude><size><![CDATA[292229]]></size><width><![CDATA[922]]></width><height><![CDATA[692]]></height><width>922</width><height>692</height><size>292229</size></item><item><filename><![CDATA[ksgagro-gallery/3.jpg]]></filename><title><![CDATA[]]></title><tags><![CDATA[]]></tags><description><![CDATA[]]></description><longitude><![CDATA[]]></longitude><latitude><![CDATA[]]></latitude><size><![CDATA[149074]]></size><width><![CDATA[922]]></width><height><![CDATA[692]]></height><width>922</width><height>692</height><size>149074</size></item><item><filename><![CDATA[ksgagro-gallery/4.jpg]]></filename><title><![CDATA[]]></title><tags><![CDATA[]]></tags><description><![CDATA[]]></description><longitude><![CDATA[]]></longitude><latitude><![CDATA[]]></latitude><size><![CDATA[131816]]></size><width><![CDATA[648]]></width><height><![CDATA[780]]></height><width>648</width><height>780</height><size>131816</size></item><item><filename><![CDATA[ksgagro-gallery/5.jpg]]></filename><title><![CDATA[]]></title><tags><![CDATA[]]></tags><description><![CDATA[]]></description><longitude><![CDATA[]]></longitude><latitude><![CDATA[]]></latitude><size><![CDATA[94079]]></size><width><![CDATA[922]]></width><height><![CDATA[692]]></height><width>922</width><height>692</height><size>94079</size></item><item><filename><![CDATA[ksgagro-gallery/6.jpg]]></filename><title><![CDATA[]]></title><tags><![CDATA[]]></tags><description><![CDATA[]]></description><longitude><![CDATA[]]></longitude><latitude><![CDATA[]]></latitude><size><![CDATA[188148]]></size><width><![CDATA[648]]></width><height><![CDATA[780]]></height><width>648</width><height>780</height><size>188148</size></item><item><filename><![CDATA[ksgagro-gallery/7.jpg]]></filename><title><![CDATA[]]></title><tags><![CDATA[]]></tags><description><![CDATA[]]></description><longitude><![CDATA[]]></longitude><latitude><![CDATA[]]></latitude><size><![CDATA[126409]]></size><width><![CDATA[922]]></width><height><![CDATA[692]]></height><width>922</width><height>692</height><size>126409</size></item></gallery>
