<?xml version="1.0" encoding="UTF-8"?>
<item><pubDate>Fri, 14 Feb 2014 13:54:23 +0100</pubDate><creDate>Fri, 14 Feb 2014 11:50:19 +0100</creDate><title><![CDATA[News - Installation and start-up of pellet production plant in Vinnytsia, UA – 08.2013]]></title><url><![CDATA[news-20131209-1449_en]]></url><metad><![CDATA[]]></metad><menuOrder><![CDATA[0]]></menuOrder><template><![CDATA[news.php]]></template><content><![CDATA[&lt;p&gt;We would like to inform that Andrzej Rogulski DORAN in july 2013 completed the other project for construction of biomass processing plant in Ukraine.&lt;/p&gt;
&lt;p&gt;More information can be found at our website dedicated to projects being realized - &lt;a href=&quot;projects-ltdvinnytsa-pelletplant&quot;&gt;click here&lt;/a&gt;.&lt;/p&gt;
]]></content><author><![CDATA[doran]]></author><parent><![CDATA[]]></parent><meta><![CDATA[_special_news, news, vinnytsa]]></meta><special><![CDATA[news]]></special><user><![CDATA[doran]]></user><menu><![CDATA[News - Installation and start-up of pellet production plant in Vinnytsia, UA &ndash; 08.2013]]></menu><menuStatus><![CDATA[]]></menuStatus><private><![CDATA[]]></private></item>
